blockchain_linker/__init__.py
blockchain_linker/blockchain.py
blockchain_linker/utils.py
blockchain_linker-0.1.0.dist-info/METADATA
blockchain_linker-0.1.0.dist-info/WHEEL
blockchain_linker-0.1.0.dist-info/top_level.txt
blockchain_linker-0.1.0.dist-info/RECORD
