Metadata-Version: 2.4
Name: blockchain_linker
Version: 0.1.0
Summary: 사용자 정보를 블록체인으로 만들어주는 Python 패키지
Home-page: https://github.com/lee-seokmin/blockchain_linker
Author: lee-seokmin
Author-email: dltjrals13@naver.com
Classifier: Programming Language :: Python :: 3
Classifier: License :: OSI Approved :: MIT License
Classifier: Operating System :: OS Independent
Requires-Python: >=3.7
Dynamic: author
Dynamic: author-email
Dynamic: classifier
Dynamic: description
Dynamic: description-content-type
Dynamic: home-page
Dynamic: requires-python
Dynamic: summary
